phdi/__init__.py
phdi/cloud/README.md
phdi/cloud/__init__.py
phdi/cloud/azure.py
phdi/cloud/core.py
phdi/cloud/gcp.py
phdi/containers/README.md
phdi/containers/__init__.py
phdi/containers/base_service.py
phdi/fhir/__init__.py
phdi/fhir/cloud/README.md
phdi/fhir/cloud/__init__.py
phdi/fhir/cloud/azure.py
phdi/fhir/conversion/README.md
phdi/fhir/conversion/__init__.py
phdi/fhir/conversion/convert.py
phdi/fhir/geospatial/README.md
phdi/fhir/geospatial/__init__.py
phdi/fhir/geospatial/census.py
phdi/fhir/geospatial/core.py
phdi/fhir/geospatial/smarty.py
phdi/fhir/harmonization/README.md
phdi/fhir/harmonization/__init__.py
phdi/fhir/harmonization/standardization.py
phdi/fhir/linkage/__init__.py
phdi/fhir/linkage/link.py
phdi/fhir/tabulation/README.md
phdi/fhir/tabulation/__init__.py
phdi/fhir/tabulation/tables.py
phdi/fhir/transport/README.md
phdi/fhir/transport/__init__.py
phdi/fhir/transport/export.py
phdi/fhir/transport/http.py
phdi/fhir/utils.py
phdi/geospatial/README.md
phdi/geospatial/__init__.py
phdi/geospatial/census.py
phdi/geospatial/core.py
phdi/geospatial/smarty.py
phdi/harmonization/README.md
phdi/harmonization/__init__.py
phdi/harmonization/double_metaphone.py
phdi/harmonization/hl7.py
phdi/harmonization/phdi_nicknames.csv
phdi/harmonization/standardization.py
phdi/harmonization/utils.py
phdi/linkage/README.md
phdi/linkage/__init__.py
phdi/linkage/algorithms.py
phdi/linkage/config.py
phdi/linkage/core.py
phdi/linkage/dal.py
phdi/linkage/link.py
phdi/linkage/mpi.py
phdi/linkage/new_tables.ddl
phdi/linkage/seed.py
phdi/linkage/utils.py
phdi/tabulation/README.md
phdi/tabulation/__init__.py
phdi/tabulation/tables.py
phdi/tabulation/validation_schema.json
phdi/transport/README.md
phdi/transport/__init__.py
phdi/transport/http.py
phdi/validation/__init__.py
phdi/validation/validation.py
phdi/validation/xml_utils.py
phdi-1.7.6.dist-info/LICENSE.md
phdi-1.7.6.dist-info/METADATA
phdi-1.7.6.dist-info/WHEEL
phdi-1.7.6.dist-info/RECORD
