Metadata-Version: 2.1
Name: phdi
Version: 1.7.6
Summary: Public health data infrastructure Building Blocks is a library to help public health departments work with their data
Home-page: https://github.com/CDCgov/phdi
Author: Kenneth Chow
Author-email: kenneth@skylight.digital
Requires-Python: >=3.10,<4.0
Classifier: Programming Language :: Python :: 3
Classifier: Programming Language :: Python :: 3.10
Classifier: Programming Language :: Python :: 3.11
Classifier: Programming Language :: Python :: 3.12
Classifier: Programming Language :: Python :: 3.13
Requires-Dist: PyYAML (>=6.0,<7.0)
Requires-Dist: azure-identity (>=1.10.0,<2.0.0)
Requires-Dist: azure-keyvault-secrets (>=4.7.0,<5.0.0)
Requires-Dist: azure-storage-blob (>=12.12.0,<13.0.0)
Requires-Dist: coverage (>=6.4.1,<7.0.0)
Requires-Dist: detect-delimiter (>=0.1.1,<0.2.0)
Requires-Dist: faker (>=18.4.0,<19.0.0)
Requires-Dist: fastapi (>=0.109.1,<0.110)
Requires-Dist: fhirpathpy (>=0.1.0,<0.2.0)
Requires-Dist: google-auth (>=2.10.0,<3.0.0)
Requires-Dist: google-cloud-storage (>=2.5.0,<3.0.0)
Requires-Dist: hl7 (>=0.4.5,<0.5.0)
Requires-Dist: httpx (>=0.24.0,<0.25.0)
Requires-Dist: jsonschema (==4.16.0)
Requires-Dist: lxml (>=4.9.2,<5.0.0)
Requires-Dist: matplotlib (>=3.7.1,<4.0.0)
Requires-Dist: pandas (>=1.4.2,<2.0.0)
Requires-Dist: phonenumbers (>=8.12.48,<9.0.0)
Requires-Dist: pillow (>=10.3.0,<11.0.0)
Requires-Dist: polling (>=0.3.2,<0.4.0)
Requires-Dist: psycopg2-binary (>=2.9.5,<3.0.0)
Requires-Dist: pyarrow (>=12,<15)
Requires-Dist: pycountry (>=22.3.5,<23.0.0)
Requires-Dist: pydantic (>=1.10.9,<2.0.0)
Requires-Dist: rapidfuzz (>=2.13.6,<3.0.0)
Requires-Dist: smartystreets-python-sdk (>=4.10.6,<5.0.0)
Requires-Dist: sqlalchemy (>=2.0.0,<3.0.0)
Project-URL: Documentation, https://cdcgov.github.io/phdi
Project-URL: Repository, https://github.com/CDCgov/phdi
